templatest/__init__.py
templatest/_abc.py
templatest/_collections.py
templatest/_objects.py
templatest/_version.py
templatest/exceptions.py
templatest/py.typed
templatest/templates.py
templatest/utils.py
templatest-0.12.0.dist-info/LICENSE
templatest-0.12.0.dist-info/METADATA
templatest-0.12.0.dist-info/WHEEL
templatest-0.12.0.dist-info/RECORD
