Metadata-Version: 2.1
Name: templatest
Version: 0.12.0
Summary: Templates for testing with strings
Home-page: https://pypi.org/project/templatest/
License: MIT
Keywords: expected,pytest,strings,template,unittest
Author: jshwi
Author-email: stephen@jshwisolutions.com
Maintainer: jshwi
Maintainer-email: stephen@jshwisolutions.com
Requires-Python: >=3.10,<4.0
Classifier: License :: OSI Approved :: MIT License
Classifier: Programming Language :: Python :: 3
Classifier: Programming Language :: Python :: 3.10
Classifier: Programming Language :: Python :: 3.11
Classifier: Programming Language :: Python :: 3.12
Requires-Dist: typing-extensions (>=4.8.0,<5.0.0)
Project-URL: Documentation, https://templatest.readthedocs.io/en/latest
Project-URL: Repository, https://github.com/jshwi/templatest
